colcon_uv/__init__.py
colcon_uv/cli.py
colcon_uv/dependencies/__init__.py
colcon_uv/dependencies/install.py
colcon_uv/package_augmentation/__init__.py
colcon_uv/package_augmentation/uv.py
colcon_uv/package_identification/__init__.py
colcon_uv/package_identification/uv.py
colcon_uv/task/__init__.py
colcon_uv/task/uv/__init__.py
colcon_uv/task/uv/build.py
colcon_uv/task/uv/test.py
colcon_uv-0.0.1.dist-info/METADATA
colcon_uv-0.0.1.dist-info/WHEEL
colcon_uv-0.0.1.dist-info/entry_points.txt
colcon_uv-0.0.1.dist-info/RECORD
