Metadata-Version: 2.4
Name: colcon-uv
Version: 0.0.1
Summary: A Colcon extension providing support for Python projects that use UV
Project-URL: Homepage, https://github.com/nzlz/colcon-uv
Author-email: Nestor Gonzalez <nestor94gonzalez@gmail.com>
Maintainer-email: Nestor Gonzalez <nestor94gonzalez@gmail.com>
License: BSD-3-Clause
Keywords: colcon
Classifier: Development Status :: 3 - Alpha
Classifier: Environment :: Plugins
Classifier: Intended Audience :: Developers
Classifier: License :: OSI Approved :: BSD License
Classifier: Programming Language :: Python
Classifier: Topic :: Software Development :: Build Tools
Requires-Dist: colcon-core~=0.6
Requires-Dist: tomli>=1.2.0
